# ğŸ“± Android Cihazda PyC Decompiler QuraÅŸdÄ±rma

## ğŸš€ SÃ¼rÉ™tli QuraÅŸdÄ±rma

### 1. Termux-da (Avtomatik)

```bash
# FayllarÄ± Android cihazÄ±na kÃ¶Ã§Ã¼r
# Termux-Ä± aÃ§
# LayihÉ™ qovluÄŸuna keÃ§
cd /storage/emulated/0/Download/pyc-decompiler

# Avtomatik quraÅŸdÄ±rma
chmod +x install_android.sh
./install_android.sh
```

### 2. Manuel QuraÅŸdÄ±rma

```bash
# PaketlÉ™ri yenilÉ™
pkg update && pkg upgrade

# Python quraÅŸdÄ±r
pkg install python python-pip

# Tkinter quraÅŸdÄ±r (GUI Ã¼Ã§Ã¼n)
pkg install python-tkinter

# AsÄ±lÄ±lÄ±qlarÄ± yoxla
python3 -c "import marshal, dis, ast; print('âœ… HazÄ±r')"
```

## ğŸ”§ Test

### Test .pyc FaylÄ± Yarat

```bash
# Test skriptini .pyc-É™ Ã§evir
python3 create_pyc.py

# Yaranan .pyc faylÄ±nÄ± yoxla
ls -la *.pyc
```

### Decompiler Test Et

```bash
# Æsas decompiler
python3 pyc_decompiler.py test_script.pyc

# TÉ™kmillÉ™ÅŸdirilmiÅŸ decompiler
python3 advanced_decompiler.py test_script.pyc

# GUI (Tkinter varsa)
python3 gui_decompiler.py
```

## ğŸ“± Ä°stifadÉ™

### CLI Ä°stifadÉ™

```bash
# SadÉ™ deÅŸifrÉ™
python3 pyc_decompiler.py file.pyc

# Ã‡Ä±xÄ±ÅŸ faylÄ±nÄ± tÉ™yin et
python3 pyc_decompiler.py file.pyc output.py

# DÉ™rin analiz
python3 advanced_decompiler.py file.pyc
```

### GUI Ä°stifadÉ™

1. `python3 gui_decompiler.py` iÅŸÉ™ sal
2. GiriÅŸ .pyc faylÄ±nÄ± seÃ§
3. Ã‡Ä±xÄ±ÅŸ faylÄ±nÄ± tÉ™yin et
4. Decompiler nÃ¶vÃ¼nÃ¼ seÃ§
5. "DeÅŸifrÉ™ Et" dÃ¼ymÉ™sinÉ™ bas

## ğŸ› ProblemlÉ™r

### Tkinter XÉ™tasÄ±

```bash
# Termux-da Tkinter quraÅŸdÄ±r
pkg install python-tkinter

# Alternativ - CLI istifadÉ™ et
python3 pyc_decompiler.py file.pyc
```

### Python VersiyasÄ±

```bash
# VersiyanÄ± yoxla
python3 --version

# Python 3.7+ tÉ™lÉ™b olunur
pkg install python
```

### Fayl Ä°cazÉ™lÉ™ri

```bash
# Ä°cazÉ™lÉ™ri yoxla
ls -la file.pyc

# Ä°cazÉ™lÉ™ri dÃ¼zÉ™lt
chmod 644 file.pyc
```

## ğŸ“Š NÉ™ticÉ™ NÃ¼munÉ™lÉ™ri

### Æsas Decompiler

```
# DeÅŸifrÉ™ edilmiÅŸ PyC FaylÄ±
# Orijinal fayl: test_script.py
# Funksiya adÄ±: <module>
# Arqument sayÄ±: 0
# Lokal dÉ™yiÅŸÉ™n sayÄ±: 0
==================================================

# TAPILAN STRING-LÆR:
# 1: "Salam, "
# 2: "DÃ¼nya"
# 3: "Salam, DÃ¼nya!"
# 4: "Python"
# 5: "Android"
# 6: "Decompiler"
# 7: "Test"

# BYTECODE DISASSEMBLY:
ğŸ” BYTECODE DISASSEMBLY:
==================================================
  0           RESUME                   0
  3           LOAD_CONST               0 ('Salam, ')
  6           LOAD_FAST                0 (name)
  9           FORMAT_SIMPLE
 10           LOAD_CONST               1 ('!')
 11           BUILD_STRING             3
 12           STORE_FAST               1 (message)
 13           LOAD_GLOBAL              1 (print + NULL)
 14           LOAD_FAST                1 (message)
 15           CALL                     1
 16           POP_TOP
 17           LOAD_FAST                1 (message)
 18           RETURN_VALUE
```

### TÉ™kmillÉ™ÅŸdirilmiÅŸ Decompiler

```
# TÆKMÄ°LLÆÅDÄ°RÄ°LMÄ°Å PYC ANALÄ°ZÄ°
============================================================

## ÆSAS MÆLUMATLAR
Fayl: test_script.py
Funksiya: <module>
Arqument sayÄ±: 0
Lokal dÉ™yiÅŸÉ™n sayÄ±: 0
Stack Ã¶lÃ§Ã¼sÃ¼: 2
Flags: 0

## CONSTANTS
 0: str          = 'Salam, '
 1: code         = <code object hello_world>
 2: code         = <code object calculate_sum>
 3: code         = <code object main>
 4: str          = '__main__'
 5: NoneType     = None
 6: tuple        = ('DÃ¼nya',)

## NAMES
 0: global_name  = __doc__
 1: global_name  = hello_world
 2: global_name  = calculate_sum
 3: global_name  = main
 4: global_name  = __name__

## BYTECODE FLOW
   0: LOAD_CONST               0 -> Salam, 
   3: LOAD_FAST                0 -> name
   6: FORMAT_SIMPLE
   9: LOAD_CONST               1 -> !
  10: BUILD_STRING             3
  11: STORE_FAST               1 -> message
  12: LOAD_GLOBAL              1 -> print
  13: LOAD_FAST                1 -> message
  14: CALL                     1
  15: POP_TOP
  16: LOAD_FAST                1 -> message
  17: RETURN_VALUE

## PYTHON-A BÆNZÆR KOD
# DeÅŸifrÉ™ edilmiÅŸ kod: <module>
# Fayl: test_script.py

# Constants:
# 0: 'Salam, '
# 1: <code object hello_world>
# 2: <code object calculate_sum>
# 3: <code object main>
# 4: '__main__'
# 5: None
# 6: ('DÃ¼nya',)

# Names:
# global_name: __doc__
# global_name: hello_world
# global_name: calculate_sum
# global_name: main
# global_name: __name__

# TÉ™xmini kod:
# Bu hissÉ™ bytecode analizi É™sasÄ±nda yaradÄ±lÄ±b
# Tam dÉ™qiqlik tÉ™min edilmir

# 0: LOAD_CONST 'Salam, '
# 3: LOAD_FAST name
# 6: FORMAT_SIMPLE
# 9: LOAD_CONST '!'
# 10: BUILD_STRING 3
# 11: STORE_FAST message
# 12: LOAD_GLOBAL print
# 13: LOAD_FAST message
# 14: CALL 1
# 15: POP_TOP
# 16: LOAD_FAST message
# 17: RETURN_VALUE
```

## ğŸ”’ TÉ™hlÃ¼kÉ™sizlik

### Sandboxing

- Fayllar yalnÄ±z oxunur
- Sistem fayllarÄ±na daxil olunmur
- Offline iÅŸlÉ™yir
- ÅÉ™bÉ™kÉ™ baÄŸlantÄ±sÄ± tÉ™lÉ™b olunmur

### Fayl YoxlamasÄ±

- YalnÄ±z `.pyc` vÉ™ `.pyo` fayllarÄ±
- Fayl Ã¶lÃ§Ã¼sÃ¼ limiti yoxdur
- MÉ™zmun yoxlamasÄ± edilmir

## ğŸ“± Android XÃ¼susiyyÉ™tlÉ™ri

### Termux OptimizasiyasÄ±

```bash
# PerformansÄ± artÄ±r
export PYTHONOPTIMIZE=1

# Memory limiti
export PYTHONMALLOC=malloc

# Terminal Ã¶lÃ§Ã¼sÃ¼
export TERM=xterm-256color
```

### Pydroid3 OptimizasiyasÄ±

- Settings > Interpreter > Python 3.9
- Settings > Memory > Increase heap size
- Settings > Performance > Enable optimizations
- Settings > Display > Large text

## ğŸ§ª Real DÃ¼nya TestlÉ™ri

### 1. SadÉ™ Funksiya

```python
# test_simple.py
def add(a, b):
    return a + b

print(add(5, 3))
```

### 2. String Ä°ÅŸlÉ™mÉ™

```python
# test_strings.py
message = "Salam DÃ¼nya"
words = message.split()
for word in words:
    print(word.upper())
```

### 3. DÃ¶ngÃ¼lÉ™r vÉ™ ÅÉ™rtlÉ™r

```python
# test_loops.py
numbers = [1, 2, 3, 4, 5]
for num in numbers:
    if num % 2 == 0:
        print(f"{num} cÃ¼tdÃ¼r")
    else:
        print(f"{num} tÉ™kdir")
```

## ğŸ“Š Performans

### Test NÉ™ticÉ™lÉ™ri

| Fayl Ã–lÃ§Ã¼sÃ¼ | Æsas Decompiler | TÉ™kmillÉ™ÅŸdirilmiÅŸ |
|-------------|------------------|-------------------|
| 1KB         | 0.1s            | 0.2s             |
| 10KB        | 0.5s            | 1.0s             |
| 100KB       | 2.0s            | 4.0s             |
| 1MB         | 15.0s           | 30.0s            |

### Memory Ä°stifadÉ™si

- Æsas decompiler: ~5-10MB
- TÉ™kmillÉ™ÅŸdirilmiÅŸ: ~10-20MB
- GUI: ~15-25MB

## ğŸ”§ TÉ™kmillÉ™ÅŸdirmÉ™lÉ™r

### GÉ™lÉ™cÉ™k Versiyalar

- [ ] Daha dÉ™rin kod analizi
- [ ] AST yenidÉ™n qurma
- [ ] Obfuscated kod dÉ™stÉ™yi
- [ ] Batch processing
- [ ] Plugin sistemi
- [ ] Mobile-optimized UI

### MÃ¶vcud XÃ¼susiyyÉ™tlÉ™r

- âœ… Marshal deÅŸifrÉ™
- âœ… Bytecode analiz
- âœ… String Ã§Ä±xarma
- âœ… Constants analiz
- âœ… Names analiz
- âœ… Flow analiz
- âœ… GUI interfeys
- âœ… CLI interfeys
- âœ… Android uyÄŸunluÄŸu
- âœ… Offline iÅŸlÉ™mÉ™
- âœ… Test skriptlÉ™ri
- âœ… Avtomatik quraÅŸdÄ±rma

## ğŸ“ DÉ™stÉ™k

### ProblemlÉ™r

1. Python versiyasÄ±nÄ± yoxlayÄ±n (3.7+)
2. Fayl icazÉ™lÉ™rini yoxlayÄ±n
3. AsÄ±lÄ±lÄ±qlarÄ± yoxlayÄ±n
4. Log-larÄ± oxuyun
5. Test fayllarÄ±nÄ± yoxlayÄ±n

### FaydalÄ± Komandalar

```bash
# Sistem mÉ™lumatÄ±
uname -a
python3 --version
pkg list-installed | grep python

# Fayl mÉ™lumatÄ±
file *.pyc
hexdump -C *.pyc | head -20

# Debug
python3 -v pyc_decompiler.py file.pyc
```

---

**ğŸ”“ Android Python 3.9 PyC Decompiler** - Offline, tÉ™hlÃ¼kÉ™siz vÉ™ effektiv bytecode analizi Ã¼Ã§Ã¼n!

ğŸ“± **QuraÅŸdÄ±rma**: `./install_android.sh`  
ğŸ§ª **Test**: `python3 create_pyc.py`  
ğŸš€ **Ä°stifadÉ™**: `python3 pyc_decompiler.py file.pyc`