# ğŸ”“ Android Python 3.9 PyC Decompiler

Android cihazda Python 3.9 ilÉ™ marshal modulu ilÉ™ ÅŸifrÉ™lÉ™nmiÅŸ `.pyc` vÉ™ ya bytecode fayllarÄ±nÄ± deÅŸifrÉ™ etmÉ™k Ã¼Ã§Ã¼n tam hÉ™ll.

## ğŸ“± DÉ™stÉ™klÉ™nÉ™n MÃ¼hitlÉ™r

- **Termux** (Android terminal emulyatoru)
- **Pydroid3** (Android Python IDE)
- **QPython** (Android Python)
- **Pythonista** (iOS - É™lavÉ™ dÉ™stÉ™k)

## ğŸš€ QuraÅŸdÄ±rma

### Termux-da

```bash
# PaketlÉ™ri yenilÉ™
pkg update && pkg upgrade

# Python vÉ™ lazÄ±mi paketlÉ™ri quraÅŸdÄ±r
pkg install python python-pip

# Tkinter quraÅŸdÄ±r (GUI Ã¼Ã§Ã¼n)
pkg install python-tkinter

# LayihÉ™ni klonla vÉ™ ya yÃ¼klÉ™
cd /storage/emulated/0/Download
git clone <repository_url>
cd pyc-decompiler

# AsÄ±lÄ±lÄ±qlarÄ± yoxla
python3 -c "import marshal, dis, ast; print('âœ… BÃ¼tÃ¼n modullar mÃ¶vcuddur')"
```

### Pydroid3-dÉ™

1. Pydroid3-Ã¼ Google Play Store-dan yÃ¼klÉ™
2. LayihÉ™ fayllarÄ±nÄ± Android cihazÄ±na kÃ¶Ã§Ã¼r
3. Pydroid3-dÉ™ fayllarÄ± aÃ§

## ğŸ“ Fayl Strukturu

```
pyc-decompiler/
â”œâ”€â”€ pyc_decompiler.py          # Æsas decompiler
â”œâ”€â”€ advanced_decompiler.py     # TÉ™kmillÉ™ÅŸdirilmiÅŸ decompiler
â”œâ”€â”€ gui_decompiler.py         # GUI interfeys
â”œâ”€â”€ test_script.py            # Test skripti
â”œâ”€â”€ create_pyc.py             # .pyc yaradÄ±cÄ±
â””â”€â”€ README.md                 # Bu fayl
```

## ğŸ”§ Ä°stifadÉ™

### 1. Æsas Decompiler (CLI)

```bash
# SadÉ™ deÅŸifrÉ™
python3 pyc_decompiler.py input.pyc

# Ã‡Ä±xÄ±ÅŸ faylÄ±nÄ± tÉ™yin et
python3 pyc_decompiler.py input.pyc output.py

# Test
python3 pyc_decompiler.py test_script.pyc
```

### 2. TÉ™kmillÉ™ÅŸdirilmiÅŸ Decompiler

```bash
# DÉ™rin analiz
python3 advanced_decompiler.py input.pyc

# Ã‡Ä±xÄ±ÅŸ faylÄ±nÄ± tÉ™yin et
python3 advanced_decompiler.py input.pyc output.py

# Test
python3 advanced_decompiler.py test_script.pyc
```

### 3. GUI Ä°nterfeys

```bash
# GUI baÅŸlat
python3 gui_decompiler.py
```

## ğŸ§ª Test

### Test .pyc FaylÄ± Yarat

```bash
# Test skriptini .pyc-É™ Ã§evir
python3 create_pyc.py

# Yaranan .pyc faylÄ±nÄ± deÅŸifrÉ™ et
python3 pyc_decompiler.py test_script.pyc
python3 advanced_decompiler.py test_script.pyc
```

### Test Skripti

`test_script.py` faylÄ±nda:
- Funksiyalar
- String-lÉ™r
- Hesablamalar
- DÃ¶ngÃ¼lÉ™r

## ğŸ“Š Ã‡Ä±xÄ±ÅŸ FormatlarÄ±

### Æsas Decompiler

```
# DeÅŸifrÉ™ edilmiÅŸ PyC FaylÄ±
# Orijinal fayl: test_script.py
# Funksiya adÄ±: <module>
# Arqument sayÄ±: 0
# Lokal dÉ™yiÅŸÉ™n sayÄ±: 0
==================================================

# TAPILAN STRING-LÆR:
# 1: "Salam, "
# 2: "DÃ¼nya"
# 3: "Salam, DÃ¼nya!"
# 4: "Python"
# 5: "Android"
# 6: "Decompiler"
# 7: "Test"

# BYTECODE DISASSEMBLY:
# Bu hissÉ™ni Python bytecode kimi iÅŸlÉ™tmÉ™k olar
ğŸ” BYTECODE DISASSEMBLY:
==================================================
```

### TÉ™kmillÉ™ÅŸdirilmiÅŸ Decompiler

```
# TÆKMÄ°LLÆÅDÄ°RÄ°LMÄ°Å PYC ANALÄ°ZÄ°
============================================================

## ÆSAS MÆLUMATLAR
Fayl: test_script.py
Funksiya: <module>
Arqument sayÄ±: 0
Lokal dÉ™yiÅŸÉ™n sayÄ±: 0
Stack Ã¶lÃ§Ã¼sÃ¼: 3
Flags: 64

## CONSTANTS
 0: str         = 'Salam, '
 1: str         = 'DÃ¼nya'
 2: str         = 'Salam, DÃ¼nya!'
 3: str         = 'Python'
 4: str         = 'Android'
 5: str         = 'Decompiler'
 6: str         = 'Test'

## NAMES
 0: global_name = print
 1: global_name = hello_world
 2: global_name = calculate_sum
 3: global_name = main

## BYTECODE FLOW
   0: LOAD_CONST               0 -> Salam, 
   3: LOAD_CONST               1 -> DÃ¼nya
   6: LOAD_CONST               2 -> Salam, DÃ¼nya!
   9: LOAD_CONST               3 -> Python
  12: LOAD_CONST               4 -> Android
  15: LOAD_CONST               5 -> Decompiler
  18: LOAD_CONST               6 -> Test
  21: BUILD_LIST               7
  24: STORE_NAME              0 -> print
  27: STORE_NAME              1 -> hello_world
  30: STORE_NAME              2 -> calculate_sum
  33: STORE_NAME              3 -> main
  36: LOAD_NAME               3 -> main
  39: CALL_FUNCTION           0
  42: POP_TOP
  43: LOAD_CONST               7 -> None
  46: RETURN_VALUE

## PYTHON-A BÆNZÆR KOD
# DeÅŸifrÉ™ edilmiÅŸ kod: <module>
# Fayl: test_script.py

# Constants:
# 0: 'Salam, '
# 1: 'DÃ¼nya'
# 2: 'Salam, DÃ¼nya!'
# 3: 'Python'
# 4: 'Android'
# 5: 'Decompiler'
# 6: 'Test'

# Names:
# global_name: print
# global_name: hello_world
# global_name: calculate_sum
# global_name: main

# TÉ™xmini kod:
# Bu hissÉ™ bytecode analizi É™sasÄ±nda yaradÄ±lÄ±b
# Tam dÉ™qiqlik tÉ™min edilmir

# 0: LOAD_CONST 'Salam, '
# 3: LOAD_CONST 'DÃ¼nya'
# 6: LOAD_CONST 'Salam, DÃ¼nya!'
# 9: LOAD_CONST 'Python'
# 12: LOAD_CONST 'Android'
# 15: LOAD_CONST 'Decompiler'
# 18: LOAD_CONST 'Test'
# 21: BUILD_LIST 7
# 24: STORE_NAME 'print'
# 27: STORE_NAME 'hello_world'
# 30: STORE_NAME 'calculate_sum'
# 33: STORE_NAME 'main'
# 36: LOAD_NAME 'main'
# 39: CALL_FUNCTION(0)
# 42: POP_TOP
# 43: LOAD_CONST None
# 46: RETURN_VALUE
```

## ğŸ”’ TÉ™hlÃ¼kÉ™sizlik

### Sandboxing

- Fayllar yalnÄ±z oxunur
- Sistem fayllarÄ±na daxil olunmur
- Offline iÅŸlÉ™yir
- ÅÉ™bÉ™kÉ™ baÄŸlantÄ±sÄ± tÉ™lÉ™b olunmur

### Fayl YoxlamasÄ±

- YalnÄ±z `.pyc` vÉ™ `.pyo` fayllarÄ±
- Fayl Ã¶lÃ§Ã¼sÃ¼ limiti yoxdur
- MÉ™zmun yoxlamasÄ± edilmir

## ğŸ› ProblemlÉ™r vÉ™ HÉ™llÉ™r

### Tkinter XÉ™tasÄ±

```bash
# Termux-da
pkg install python-tkinter

# Alternativ - CLI istifadÉ™ et
python3 pyc_decompiler.py file.pyc
```

### Marshal XÉ™tasÄ±

```bash
# Python versiyasÄ±nÄ± yoxla
python3 --version

# Python 3.7+ tÉ™lÉ™b olunur
pkg install python
```

### Fayl Oxuma XÉ™tasÄ±

```bash
# Fayl mÃ¶vcudluÄŸunu yoxla
ls -la file.pyc

# Ä°cazÉ™lÉ™ri yoxla
chmod 644 file.pyc
```

## ğŸ“± Android XÃ¼susiyyÉ™tlÉ™ri

### Termux OptimizasiyasÄ±

```bash
# PerformansÄ± artÄ±r
export PYTHONOPTIMIZE=1

# Memory limiti
export PYTHONMALLOC=malloc
```

### Pydroid3 OptimizasiyasÄ±

- Settings > Interpreter > Python 3.9
- Settings > Memory > Increase heap size
- Settings > Performance > Enable optimizations

## ğŸ”§ TÉ™kmillÉ™ÅŸdirmÉ™lÉ™r

### GÉ™lÉ™cÉ™k Versiyalar

- [ ] Daha dÉ™rin kod analizi
- [ ] AST yenidÉ™n qurma
- [ ] Obfuscated kod dÉ™stÉ™yi
- [ ] Batch processing
- [ ] Plugin sistemi

### MÃ¶vcud XÃ¼susiyyÉ™tlÉ™r

- âœ… Marshal deÅŸifrÉ™
- âœ… Bytecode analiz
- âœ… String Ã§Ä±xarma
- âœ… Constants analiz
- âœ… Names analiz
- âœ… Flow analiz
- âœ… GUI interfeys
- âœ… CLI interfeys
- âœ… Android uyÄŸunluÄŸu
- âœ… Offline iÅŸlÉ™mÉ™

## ğŸ“ DÉ™stÉ™k

### ProblemlÉ™r

1. Python versiyasÄ±nÄ± yoxlayÄ±n (3.7+)
2. Fayl icazÉ™lÉ™rini yoxlayÄ±n
3. AsÄ±lÄ±lÄ±qlarÄ± yoxlayÄ±n
4. Log-larÄ± oxuyun

### TÉ™limatlar

- [Python 3.9 QuraÅŸdÄ±rma](https://wiki.termux.com/wiki/Python)
- [Termux Tkinter](https://wiki.termux.com/wiki/Tkinter)
- [Pydroid3 QuraÅŸdÄ±rma](https://play.google.com/store/apps/details?id=ru.iiec.pydroid3)

## ğŸ“„ Lisenziya

Bu layihÉ™ MIT lisenziyasÄ± altÄ±nda yayÄ±mlanÄ±r.

## ğŸ¤ TÃ¶hfÉ™

TÉ™kmillÉ™ÅŸdirmÉ™lÉ™r Ã¼Ã§Ã¼n pull request gÃ¶ndÉ™rin.

---

**ğŸ”“ Android Python 3.9 PyC Decompiler** - Offline, tÉ™hlÃ¼kÉ™siz vÉ™ effektiv bytecode analizi Ã¼Ã§Ã¼n!